{
  "pages": [
    {
      "path": "pages/index/index",
      "style": {
        "navigationBarTitleText": "一月一露"
      }
    },
    {
      "path": "pages/category/index",
      "style": {
        "navigationBarTitleText": "分类",
        "enablePullDownRefresh": true
      }
    },
    {
      "path": "pages/cart/index",
      "style": {
        "navigationBarTitleText": "购物车"
      }
    },
    {
      "path": "pages/order/index",
      "style": {
        "navigationBarTitleText": "我的订单"
      }
    },
    {
      "path": "pages/mine/index",
      "style": {
        "navigationBarTitleText": "我的",
        "navigationStyle": "custom"
      }
    },
    {
      "path": "pages/product-detail/index",
      "style": {
        "navigationBarTitleText": "商品详情",
        "navigationStyle": "custom"
      }
    },
    {
      "path": "pages/order-confirm/index",
      "style": {
        "navigationBarTitleText": "确认订单"
      }
    },
    {
      "path": "pages/order-detail/index",
      "style": {
        "navigationBarTitleText": "订单详情"
      }
    },
    {
      "path": "pages/payment/index",
      "style": {
        "navigationBarTitleText": "支付"
      }
    },
    {
      "path": "pages/payment-result/index",
      "style": {
        "navigationBarTitleText": "支付结果"
      }
    },
    {
      "path": "pages/ticket/index",
      "style": {
        "navigationBarTitleText": "电子票"
      }
    },
    {
      "path": "pages/member/index",
      "style": {
        "navigationBarTitleText": "会员中心"
      }
    },
    {
      "path": "pages/profile/index",
      "style": {
        "navigationBarTitleText": "个人资料"
      }
    },
    {
      "path": "pages/identity/index",
      "style": {
        "navigationBarTitleText": "出行人信息"
      }
    },
    {
      "path": "pages/address/index",
      "style": {
        "navigationBarTitleText": "收货地址"
      }
    },
    {
      "path": "pages/staff/index",
      "style": {
        "navigationBarTitleText": "员工核销"
      }
    },
    {
      "path": "pages/customer-service/index",
      "style": {
        "navigationBarTitleText": "帮助与客服"
      }
    }
  ],
  "subPackages": [
    {
      "root": "pages-sub/product",
      "pages": [
        {
          "path": "camp-map/index",
          "style": { "navigationBarTitleText": "营地地图" }
        },
        {
          "path": "games/index",
          "style": { "navigationBarTitleText": "趣味游戏" }
        },
        {
          "path": "game-webview/index",
          "style": { "navigationBarTitleText": "游戏" }
        }
      ]
    }
  ],
  "globalStyle": {
    "navigationBarBackgroundColor": "#2E7D32",
    "navigationBarTitleText": "一月一露",
    "navigationBarTextStyle": "white",
    "backgroundColor": "#FFF8F0",
    "backgroundTextStyle": "dark"
  },
  "tabBar": {
    "color": "#999999",
    "selectedColor": "#2E7D32",
    "backgroundColor": "#FFFFFF",
    "borderStyle": "white",
    "list": [
      {
        "pagePath": "pages/index/index",
        "text": "首页",
        "iconPath": "static/tabs/tab-home.png",
        "selectedIconPath": "static/tabs/tab-home-active.png"
      },
      {
        "pagePath": "pages/category/index",
        "text": "分类",
        "iconPath": "static/tabs/tab-category.png",
        "selectedIconPath": "static/tabs/tab-category-active.png"
      },
      {
        "pagePath": "pages/cart/index",
        "text": "购物车",
        "iconPath": "static/tabs/tab-cart.png",
        "selectedIconPath": "static/tabs/tab-cart-active.png"
      },
      {
        "pagePath": "pages/order/index",
        "text": "订单",
        "iconPath": "static/tabs/tab-order.png",
        "selectedIconPath": "static/tabs/tab-order-active.png"
      },
      {
        "pagePath": "pages/mine/index",
        "text": "我的",
        "iconPath": "static/tabs/tab-mine.png",
        "selectedIconPath": "static/tabs/tab-mine-active.png"
      }
    ]
  }
}
